factor_analyser/FactorBacktester.py
factor_analyser/FactorFactory.py
factor_analyser/__init__.py
factor_analyser-1.0.dist-info/LICENSE
factor_analyser-1.0.dist-info/METADATA
factor_analyser-1.0.dist-info/WHEEL
factor_analyser-1.0.dist-info/top_level.txt
factor_analyser-1.0.dist-info/RECORD
