Metadata-Version: 2.1
Name: factor_analyser
Version: 1.0
Summary: A tool for factor development and analysis.
Home-page: https://github.com/AlfredCYL/factor_analyser
Author: AlfredCYL
Author-email: alfred.yl@outlook.com
Classifier: Programming Language :: Python :: 3
Classifier: License :: OSI Approved :: MIT License
Classifier: Operating System :: OS Independent
Requires-Python: >=3.6
License-File: LICENSE
Requires-Dist: numpy
Requires-Dist: pandas
Requires-Dist: matplotlib
Requires-Dist: statsmodels
Requires-Dist: tabulate
Requires-Dist: numba
